LSD11/LSD_guia_10_ERE_codigos/LSD12/divisor_clock.vhd
library ieee;
use ieee.std_logic_1164.all;
use ieee.numeric_std.all;

entity divisor_clock is
port ( clk50MHz : in std_logic;
       reset : in std_logic;
       clk1Hz : out std_logic
     );
end divisor_clock;

architecture Behavioral of divisor_clock is

--signal count : integer := 0;
signal b : std_logic := '0';
begin

 -- clk generation. For 50MHz clock this process generates 1Hz clock.
process(clk50MHz, b)
	variable cnt : integer range 0 to 2**26-1;
	begin
		if(rising_edge(clk50MHz)) then
		   if(reset = '1') then
			   cnt := 0;
			else
			   cnt := cnt + 1;
         end if;
			if(cnt = 24999999) then
				b <= not b;
				cnt := 0;
			end if;
		end if;
		clk1Hz <= b;
	end process;
end;

LSD12/semaforo.vhd
library ieee;
use ieee.std_logic_1164.all;
use ieee.numeric_std.all;

entity semaforo_fsm is
  port (
    clock     : in  std_logic;                -- Clock de entrada
    reset     : in  std_logic;                -- Sinal de reset síncrono
    led_g     : out std_logic;                -- LED verde
    led_y     : out std_logic;                -- LED amarelo
    led_r     : out std_logic;                -- LED vermelho
    seg_out   : out std_logic_vector(0 to 6)  -- Saída para o display de 7 segmentos
  );
end entity semaforo_fsm;

architecture behavioral of semaforo_fsm is
  type state_type is (s_verde, s_amarelo, s_vermelho);
  signal current_state : state_type := s_vermelho;
  signal counter : integer range 0 to 255 := 0;
  signal seg_out_internal : std_logic_vector(0 to 6) := "0000000";
  
  signal clock_div : std_logic;
  signal reset_div : std_logic;

begin

    divisor_clock_inst : entity work.divisor_clock
        port map(clk50MHz => clock, reset => reset_div, clk1Hz => clock_div);
    
  process(clock)
  begin
    if rising_edge(clock) then
      if reset_div = '1' then
        current_state <= s_vermelho;
        counter <= 0;
      else
        case current_state is
          when s_verde =>
            if counter >= 8 then
              current_state <= s_amarelo;
              counter <= 0;
            else
              counter <= counter + 1;
            end if;
          when s_amarelo =>
            if counter >= 3 then
              current_state <= s_vermelho;
              counter <= 0;
            else
              counter <= counter + 1;
            end if;
          when s_vermelho =>
            if counter >= 6 then
              current_state <= s_verde;
              counter <= 0;
            else
              counter <= counter + 1;
            end if;
        end case;
      end if;
    end if;
  end process;

  -- Lógica de controle dos LEDs com contagem regressiva
  process(current_state, counter)
  begin
    case current_state is
      when s_verde =>
        led_g <= '1';
        led_y <= '0';
        led_r <= '0';
        case counter is
          when 0 =>
          seg_out_internal <= "0000000"; -- 8
          when 1 =>
          seg_out_internal <= "0001111"; -- 7
          when 2 =>
          seg_out_internal <= "0100000"; -- 6
          when 3 =>
          seg_out_internal <= "0100100"; -- 5
          when 4 =>
          seg_out_internal <= "1001100"; -- 4
          when 5 =>
          seg_out_internal <= "0000110"; -- 3
          when 6 =>
          seg_out_internal <= "0010010"; -- 2
          when 7 =>
          seg_out_internal <= "1001111"; -- 1
          when 8 =>
          seg_out_internal <= "0000001"; -- 0  
          when others =>
            seg_out_internal <= "0001001"; -- Error
        end case;
      when s_amarelo =>
        led_g <= '0';
        led_y <= '1';
        led_r <= '0';
        case counter is
          when 0 =>
          seg_out_internal <= "0000110"; -- 3
          when 1 =>
          seg_out_internal <= "0010010"; -- 2
          when 2 =>
          seg_out_internal <= "1001111"; -- 1
          when 3 =>
          seg_out_internal <= "0000001"; -- 0  
          when others =>
            seg_out_internal <= "0001001"; -- Error
        end case;
      when s_vermelho =>
        led_g <= '0';
        led_y <= '0';
        led_r <= '1';
        case counter is
          when 0 =>
            seg_out_internal <= "0100000"; -- 6
          when 1 =>
            seg_out_internal <= "0100100"; -- 5
          when 2 =>
            seg_out_internal <= "1001100"; -- 4
          when 3 =>
            seg_out_internal <= "0000110"; -- 3
          when 4 =>
            seg_out_internal <= "0010010"; -- 2
          when 5 =>
            seg_out_internal <= "1001111"; -- 1
          when 6 =>
            seg_out_internal <= "0000001"; -- 0
when others =>
            seg_out_internal <= "0001001"; -- Error
        end case;
    end case;
  end process;

  seg_out <= seg_out_internal;
 end architecture behavioral;

Lab_SD-main/Lab_SD-main/LSD12/tb_semaforo.vhd
library ieee;
use ieee.std_logic_1164.all;

entity tb_semaforo is
end entity tb_semaforo;

architecture tb_arch of tb_semaforo is
  -- Signals
  signal clock       : std_logic := '0';
  signal reset       : std_logic := '0';
  signal led_g       : std_logic;
  signal led_y       : std_logic;
  signal led_r       : std_logic;
  signal seg_out     : std_logic_vector(6 downto 0);
  
  -- Constants
  constant CLK_PERIOD : time := 10 ns;
  
  
  begin

  -- Instantiate the DUT
  uut: entity work.semaforo_fsm
    port map (
      clock     => clock,
      reset     => reset,
      led_g     => led_g,
      led_y     => led_y,
      led_r     => led_r,
      seg_out   => seg_out
    );

  -- Clock process
  clock_process: process
  begin
    while now < 500 ns loop
      clock <= '0';
      wait for CLK_PERIOD / 2;
      clock <= '1';
      wait for CLK_PERIOD / 2;
    end loop;
    wait;
  end process clock_process;
  
  -- Stimulus process
  stimulus_process: process
  begin
    -- Reset
    reset <= '1';
    wait for 20 ns;
    reset <= '0';
    wait for 10 ns;
    
    -- Hold state s_vermelho for a while
    wait for 100 ns;
    
    -- Test s_verde state
    assert led_g = '1' and led_y = '0' and led_r = '0' and seg_out = "1001111"
      report "Error in s_verde state" severity error;
    wait for 100 ns;
    
    -- Test s_amarelo state
    assert led_g = '0' and led_y = '1' and led_r = '0' and seg_out = "0000011"
      report "Error in s_amarelo state" severity error;
    wait for 40 ns;
    
    -- Test s_vermelho state
    assert led_g = '0' and led_y = '0' and led_r = '1' and seg_out = "0111111"
      report "Error in s_vermelho state" severity error;
    wait for 70 ns;
    
    -- Test s_verde state again
    assert led_g = '1' and led_y = '0' and led_r = '0' and seg_out = "1001111"
      report "Error in s_verde state" severity error;
    wait for 90 ns;
    
    -- Finish simulation
    wait;
  end process stimulus_process;

end architecture tb_arch;

Lab_SD-main/Lab_SD-main/LSD12/tb_semaforo.vcd
$date
  Fri Jun 16 20:24:11 2023
$end
$version
  GHDL v0
$end
$timescale
  1 fs
$end
$scope module standard $end
$upscope $end
$scope module std_logic_1164 $end
$upscope $end
$scope module numeric_std $end
$upscope $end
$scope module tb_semaforo $end
$var reg 1 ! clock $end
$var reg 1 " reset $end
$var reg 1 # led_g $end
$var reg 1 $ led_y $end
$var reg 1 % led_r $end
$var reg 7 & seg_out[6:0] $end
$scope module uut $end
$var reg 1 ' clock $end
$var reg 1 ( reset $end
$var reg 1 ) led_g $end
$var reg 1 * led_y $end
$var reg 1 + led_r $end
$var reg 7 , seg_out[0:6] $end
$comment current_state is not handled $end
$var integer 32 - counter $end
$var reg 7 . seg_out_internal[0:6] $end
$var reg 1 / clock_div $end
$var reg 1 0 reset_div $end
$scope module divisor_clock_inst $end
$var reg 1 1 clk50mhz $end
$var reg 1 2 reset $end
$var reg 1 3 clk1hz $end
$var reg 1 4 b $end
$upscope $end
$upscope $end
$upscope $end
$enddefinitions $end
#0
0!
1"
0#
0$
1%
b0001111 &
0'
1(
0)
0*
1+
b0001111 ,
b0 -
b0001111 .
0/
U0
01
U2
03
04
#5000000
1!
b0100000 &
1'
b0100000 ,
b1 -
b0100000 .
11
#10000000
0!
0'
01
#15000000
1!
b0100100 &
1'
b0100100 ,
b10 -
b0100100 .
11
#20000000
0!
0"
0'
0(
01
#25000000
1!
b1001100 &
1'
b1001100 ,
b11 -
b1001100 .
11
#30000000
0!
0'
01
#35000000
1!
b0000110 &
1'
b0000110 ,
b100 -
b0000110 .
11
#40000000
0!
0'
01
#45000000
1!
b0010010 &
1'
b0010010 ,
b101 -
b0010010 .
11
#50000000
0!
0'
01
#55000000
1!
b1001111 &
1'
b1001111 ,
b110 -
b1001111 .
11
#60000000
0!
0'
01
#65000000
1!
1#
0%
b0001100 &
1'
1)
0+
b0001100 ,
b0 -
b0001100 .
11
#70000000
0!
0'
01
#75000000
1!
b0000000 &
1'
b0000000 ,
b1 -
b0000000 .
11
#80000000
0!
0'
01
#85000000
1!
b0001111 &
1'
b0001111 ,
b10 -
b0001111 .
11
#90000000
0!
0'
01
#95000000
1!
b0100000 &
1'
b0100000 ,
b11 -
b0100000 .
11
#100000000
0!
0'
01
#105000000
1!
b0100100 &
1'
b0100100 ,
b100 -
b0100100 .
11
#110000000
0!
0'
01
#115000000
1!
b1001100 &
1'
b1001100 ,
b101 -
b1001100 .
11
#120000000
0!
0'
01
#125000000
1!
b0000110 &
1'
b0000110 ,
b110 -
b0000110 .
11
#130000000
0!
0'
01
#135000000
1!
b0010010 &
1'
b0010010 ,
b111 -
b0010010 .
11
#140000000
0!
0'
01
#145000000
1!
b1001111 &
1'
b1001111 ,
b1000 -
b1001111 .
11
#150000000
0!
0'
01
#155000000
1!
0#
1$
b1001100 &
1'
0)
1*
b1001100 ,
b0 -
b1001100 .
11
#160000000
0!
0'
01
#165000000
1!
b0000110 &
1'
b0000110 ,
b1 -
b0000110 .
11
#170000000
0!
0'
01
#175000000
1!
b0010010 &
1'
b0010010 ,
b10 -
b0010010 .
11
#180000000
0!
0'
01
#185000000
1!
b1001111 &
1'
b1001111 ,
b11 -
b1001111 .
11
#190000000
0!
0'
01
#195000000
1!
0$
1%
b0001111 &
1'
0*
1+
b0001111 ,
b0 -
b0001111 .
11
#200000000
0!
0'
01
#205000000
1!
b0100000 &
1'
b0100000 ,
b1 -
b0100000 .
11
#210000000
0!
0'
01
#215000000
1!
b0100100 &
1'
b0100100 ,
b10 -
b0100100 .
11
#220000000
0!
0'
01
#225000000
1!
b1001100 &
1'
b1001100 ,
b11 -
b1001100 .
11
#230000000
0!
0'
01
#235000000
1!
b0000110 &
1'
b0000110 ,
b100 -
b0000110 .
11
#240000000
0!
0'
01
#245000000
1!
b0010010 &
1'
b0010010 ,
b101 -
b0010010 .
11
#250000000
0!
0'
01
#255000000
1!
b1001111 &
1'
b1001111 ,
b110 -
b1001111 .
11
#260000000
0!
0'
01
#265000000
1!
1#
0%
b0001100 &
1'
1)
0+
b0001100 ,
b0 -
b0001100 .
11
#270000000
0!
0'
01
#275000000
1!
b0000000 &
1'
b0000000 ,
b1 -
b0000000 .
11
#280000000
0!
0'
01
#285000000
1!
b0001111 &
1'
b0001111 ,
b10 -
b0001111 .
11
#290000000
0!
0'
01
#295000000
1!
b0100000 &
1'
b0100000 ,
b11 -
b0100000 .
11
#300000000
0!
0'
01
#305000000
1!
b0100100 &
1'
b0100100 ,
b100 -
b0100100 .
11
#310000000
0!
0'
01
#315000000
1!
b1001100 &
1'
b1001100 ,
b101 -
b1001100 .
11
#320000000
0!
0'
01
#325000000
1!
b0000110 &
1'
b0000110 ,
b110 -
b0000110 .
11
#330000000
0!
0'
01
#335000000
1!
b0010010 &
1'
b0010010 ,
b111 -
b0010010 .
11
#340000000
0!
0'
01
#345000000
1!
b1001111 &
1'
b1001111 ,
b1000 -
b1001111 .
11
#350000000
0!
0'
01
#355000000
1!
0#
1$
b1001100 &
1'
0)
1*
b1001100 ,
b0 -
b1001100 .
11
#360000000
0!
0'
01
#365000000
1!
b0000110 &
1'
b0000110 ,
b1 -
b0000110 .
11
#370000000
0!
0'
01
#375000000
1!
b0010010 &
1'
b0010010 ,
b10 -
b0010010 .
11
#380000000
0!
0'
01
#385000000
1!
b1001111 &
1'
b1001111 ,
b11 -
b1001111 .
11
#390000000
0!
0'
01
#395000000
1!
0$
1%
b0001111 &
1'
0*
1+
b0001111 ,
b0 -
b0001111 .
11
#400000000
0!
0'
01
#405000000
1!
b0100000 &
1'
b0100000 ,
b1 -
b0100000 .
11
#410000000
0!
0'
01
#415000000
1!
b0100100 &
1'
b0100100 ,
b10 -
b0100100 .
11
#420000000
0!
0'
01
#425000000
1!
b1001100 &
1'
b1001100 ,
b11 -
b1001100 .
11
#430000000
0!
0'
01
#435000000
1!
b0000110 &
1'
b0000110 ,
b100 -
b0000110 .
11
#440000000
0!
0'
01
#445000000
1!
b0010010 &
1'
b0010010 ,
b101 -
b0010010 .
11
#450000000
0!
0'
01
#455000000
1!
b1001111 &
1'
b1001111 ,
b110 -
b1001111 .
11
#460000000
0!
0'
01
#465000000
1!
1#
0%
b0001100 &
1'
1)
0+
b0001100 ,
b0 -
b0001100 .
11
#470000000
0!
0'
01
#475000000
1!
b0000000 &
1'
b0000000 ,
b1 -
b0000000 .
11
#480000000
0!
0'
01
#485000000
1!
b0001111 &
1'
b0001111 ,
b10 -
b0001111 .
11
#490000000
0!
0'
01
#495000000
1!
b0100000 &
1'
b0100000 ,
b11 -
b0100000 .
11
